hmf/__init__.py
hmf/_cli.py
hmf/_internals/__init__.py
hmf/_internals/_cache.py
hmf/_internals/_framework.py
hmf/_internals/_utils.py
hmf/alternatives/__init__.py
hmf/alternatives/wdm.py
hmf/cosmology/__init__.py
hmf/cosmology/cosmo.py
hmf/cosmology/growth_factor.py
hmf/density_field/__init__.py
hmf/density_field/filters.py
hmf/density_field/halofit.py
hmf/density_field/transfer.py
hmf/density_field/transfer_models.py
hmf/halos/__init__.py
hmf/halos/mass_definitions.py
hmf/helpers/__init__.py
hmf/helpers/cfg_utils.py
hmf/helpers/functional.py
hmf/helpers/sample.py
hmf/mass_function/__init__.py
hmf/mass_function/fitting_functions.py
hmf/mass_function/hmf.py
hmf/mass_function/integrate_hmf.py
hmf-3.5.1.dist-info/licenses/LICENSE.rst
hmf-3.5.1.dist-info/METADATA
hmf-3.5.1.dist-info/WHEEL
hmf-3.5.1.dist-info/entry_points.txt
hmf-3.5.1.dist-info/top_level.txt
hmf-3.5.1.dist-info/RECORD
