Metadata-Version: 2.4
Name: hmf
Version: 3.5.1
Summary: A halo mass function calculator
Home-page: https://github.com/steven-murray/hmf
Author: Steven Murray
Author-email: steven.g.murray@asu.edu
License: mit
Project-URL: Documentation, https://hmf.readthedocs.org
Platform: any
Classifier: Development Status :: 6 - Mature
Classifier: Programming Language :: Python :: 3.8
Classifier: Programming Language :: Python :: 3.9
Classifier: Programming Language :: Python :: 3.10
Classifier: Intended Audience :: Science/Research
Classifier: License :: OSI Approved
Classifier: License :: OSI Approved :: MIT License
Classifier: Natural Language :: English
Classifier: Topic :: Scientific/Engineering :: Physics
Classifier: Topic :: Scientific/Engineering :: Astronomy
License-File: LICENSE.rst
Requires-Dist: numpy>=1.6.2
Requires-Dist: scipy>=0.12.0
Requires-Dist: astropy>=1.1
Requires-Dist: deprecation
Requires-Dist: click
Requires-Dist: toml>=0.10.1
Requires-Dist: rich
Requires-Dist: deprecation
Requires-Dist: importlib_metadata; python_version < "3.8"
Requires-Dist: cached_property
Requires-Dist: camb>=1.0.0
Provides-Extra: docs
Requires-Dist: Sphinx>=1.7.5; extra == "docs"
Requires-Dist: numpydoc>=0.8.0; extra == "docs"
Requires-Dist: nbsphinx; extra == "docs"
Provides-Extra: tests
Requires-Dist: coverage>=4.5.1; extra == "tests"
Requires-Dist: pytest>=3.5.1; extra == "tests"
Requires-Dist: pytest-cov>=2.5.1; extra == "tests"
Requires-Dist: pre-commit; extra == "tests"
Requires-Dist: mpmath>=1.0.0; extra == "tests"
Requires-Dist: colossus>=1.2.1; extra == "tests"
Requires-Dist: halomod>=1.4.6; extra == "tests"
Requires-Dist: numba; extra == "tests"
Provides-Extra: dev
Requires-Dist: hmf[docs,tests]; extra == "dev"
Requires-Dist: setuptools_scm; extra == "dev"
Provides-Extra: cosmo
Requires-Dist: colossus>=1.2.1; extra == "cosmo"
Provides-Extra: fit
Requires-Dist: emcee>=3.0; extra == "fit"
Provides-Extra: all
Requires-Dist: hmf[cosmo,dev,fit]; extra == "all"
Dynamic: license-file
